{
	"$config": {
		"$createDate": "2014-07-15T14:15:30.000Z",
		"$lastModified": "2014-07-15T14:15:30.000Z",
		"$chapter": {
			"$name": "Admin",
			"$description": "Syracuse admin",
			"$min": 10036,
			"$max": 10043,
			"$exclude": [
				"syracuse-admin-demo.json",
				"syracuse-sprint1-demo.json",
				"x3-pages.json"
			],
			"$count": 149,
			"$lastModified": "",
			"$current": 10036,
			"$": {
				"10036": {
					"$nextId": 150
				}
			}
		},
		"$target": {},
		"$source": {
			"user": {
				"login": "erbou"
			},
			"host": {
				"name": "PO037285",
				"platform": "win32-x64"
			}
		}
	},
	"import/x3-erp-homepages.json": {
		"$key": "CEFA576D544BE7990790F11C6CA628EC654E62C5",
		"pageLayout.1228fa4b-62a1-4be5-b9f0-0ddaa4a7f80e.@3636749c-b838-49a9-9756-162bdfb014ff": {
			"chp": 10036,
			"id": 1,
			"text": {
				"en-us": "Business Process",
				"de-de": "Geschäftsprozess",
				"es-es": "Procesos",
				"fr-fr": "Processus",
				"it-it": "Business process",
				"pt-pt": "Processo de negócio"
			},
			"$key": "B7E96F5CDA87D88A9A261719DCC540EC1408F7E1"
		},
		"pageLayout.6e901b33-f32b-469b-8c25-2d83e36c9f0e.@2f7b8348-a2ed-4c63-9160-c251ee8ca7ed": {
			"chp": 10036,
			"id": 2,
			"text": {
				"en-us": "Key Information",
				"de-de": "Schlüsselinformationen",
				"es-es": "Indicadores",
				"fr-fr": "Indicateurs",
				"it-it": "Informazioni chiave",
				"pt-pt": "Informação chave"
			},
			"$key": "E840F0050F4FE85C13A97686E0071B535E66F2C6"
		},
		"pageLayout.6e901b33-f32b-469b-8c25-2d83e36c9f0e.@60e16e6e-2409-4d41-9824-fd848cad4ebd": {
			"chp": 10036,
			"id": 3,
			"text": {
				"en-us": "Business Process",
				"de-de": "Geschäftsprozess",
				"es-es": "Procesos",
				"fr-fr": "Processus",
				"it-it": "Business process",
				"pt-pt": "Processo de negócio"
			},
			"$key": "860DB36740C3EE113D987B84464C6D825B8EE549"
		},
		"pageLayout.6f5924c3-4ef3-41aa-ad4a-f6dfbc5c961e.@670737d1-c5c3-4ad9-a7b5-ad806eccbe0e": {
			"chp": 10036,
			"id": 4,
			"text": {
				"en-us": "Key Information",
				"de-de": "Schlüsselinformationen",
				"es-es": "Indicadores",
				"fr-fr": "Indicateurs",
				"it-it": "Informazioni chiave",
				"pt-pt": "Informação chave"
			},
			"$key": "24EB29BFC61F2C53A3FD752872BFDC35249C9164"
		},
		"pageLayout.6f5924c3-4ef3-41aa-ad4a-f6dfbc5c961e.@7131ffa5-b8b4-4565-b30f-9f3c14f06695": {
			"chp": 10036,
			"id": 5,
			"text": {
				"en-us": "Business processes",
				"de-de": "Geschäftsprozess",
				"es-es": "Procesos",
				"fr-fr": "Processus",
				"it-it": "Business process",
				"pt-pt": "Processo de negócio"
			},
			"$key": "A33660EB99C858D709AD68C6D4CA4CC4D71C48AF"
		},
		"pageLayout.57aa63d0-2671-4e6e-b854-417ccd7f5756.@7907c5bf-481f-4aa7-926d-04b9af25bd91": {
			"chp": 10036,
			"id": 6,
			"text": {
				"en-us": "Key Information",
				"de-de": "Schlüsselinformationen",
				"es-es": "Indicadores",
				"fr-fr": "Indicateurs",
				"it-it": "Informazioni chiave",
				"pt-pt": "Informação chave"
			},
			"$key": "AA28A99E5675705D7957AE9C9513C10337F3994F"
		},
		"pageLayout.57aa63d0-2671-4e6e-b854-417ccd7f5756.@96a2854c-8f0d-4bf9-bb10-76f5476495e9": {
			"chp": 10036,
			"id": 7,
			"text": {
				"en-us": "New Tab 1"
			},
			"$key": "D3BDD72C62FE0840D1778B36E08F48C7355C67B3"
		},
		"pageLayout.97a1fca0-634b-4498-9ece-8ce4ec526245.@98fceb07-1e7a-4680-8538-1869199c6e4f": {
			"chp": 10036,
			"id": 8,
			"text": {
				"en-us": "Business Process",
				"fr-fr": "Processus"
			},
			"$key": "6A5BA755802C0DA0D76C28B32B262FDC960451C8"
		},
		"pageLayout.97a1fca0-634b-4498-9ece-8ce4ec526245.@f126ab5b-5ef6-44c3-b7dd-5234e1965a23": {
			"chp": 10036,
			"id": 9,
			"text": {
				"en-us": "Key Information",
				"fr-fr": "Indicateurs"
			},
			"$key": "EA9FE0FC215A7F051AF12460C55D78232705EFE4"
		},
		"pageLayout.ee4ae0cf-8ecb-4820-a497-508949cb9831.@2b8229b7-b41f-46d6-bc36-adb21a0118ad": {
			"chp": 10036,
			"id": 10,
			"text": {
				"en-us": "Business process",
				"de-de": "Geschäftsprozess",
				"es-es": "Procesos",
				"fr-fr": "Processus",
				"it-it": "Business process",
				"pt-pt": "Processo de negócio"
			},
			"$key": "B30F0560CE5C563035DD31CB056F9DA6ED93D56B"
		},
		"pageLayout.ebe37ec4-ed44-4a4f-807d-f9aaa9dc37d5.@5818ee7b-6719-4092-912d-46c88a1f7d42": {
			"chp": 10036,
			"id": 11,
			"text": {
				"en-us": "Key Information",
				"de-de": "Schlüsselinformationen",
				"es-es": "Indicadores",
				"fr-fr": "Indicateurs",
				"it-it": "Informazioni chiave",
				"pt-pt": "Informação chave"
			},
			"$key": "110326B74BCF3653AA08A70C5AF6A481A454AC5C"
		},
		"pageLayout.ebe37ec4-ed44-4a4f-807d-f9aaa9dc37d5.@b45b2101-b67c-446b-9360-c95f0868a881": {
			"chp": 10036,
			"id": 12,
			"text": {
				"en-us": "Business Process",
				"de-de": "Geschäftsprozess",
				"es-es": "Procesos",
				"fr-fr": "Processus",
				"it-it": "Business process",
				"pt-pt": "Processo de negócio"
			},
			"$key": "5227D3E0EA94E8E913AD43909124D0CCCD2AAE09"
		},
		"pageLayout.25079552-a4cd-4968-b01f-ae00565809c3.@4c38c46c-927d-49fc-922e-1d1bf46c9dc2": {
			"chp": 10036,
			"id": 13,
			"text": {
				"en-us": "Key Information",
				"de-de": "Schlüsselinformationen",
				"es-es": "Indicadores",
				"fr-fr": "Indicateurs",
				"it-it": "Informazioni chiave",
				"pt-pt": "Informação chave"
			},
			"$key": "6EC08E55978742A1B1E32196C9387B08F9AB18CB"
		},
		"pageLayout.25079552-a4cd-4968-b01f-ae00565809c3.@411e1de2-1596-45dc-a8f3-9a5f378e6ad4": {
			"chp": 10036,
			"id": 14,
			"text": {
				"en-us": "Business Process",
				"de-de": "Geschäftsprozess",
				"es-es": "Procesos",
				"fr-fr": "Processus",
				"it-it": "Business process",
				"pt-pt": "Processo de negócio"
			},
			"$key": "04817D15EB86D4348E00ED0F182CF8ABED9D0BBE"
		},
		"pageLayout.46aa8540-f4a0-4b29-bfe8-2254ab6869b3.@708fd66d-38db-4dac-8c5d-5c3144c0cac8": {
			"chp": 10036,
			"id": 15,
			"text": {
				"en-us": "Key Information",
				"de-de": "Schlüsselinformationen",
				"es-es": "Indicadores",
				"fr-fr": "Indicateurs",
				"it-it": "Informazioni chiave",
				"pt-pt": "Informação chave"
			},
			"$key": "1683EF94DACD12E9634B3C8231D7F968C4A02923"
		},
		"pageLayout.46aa8540-f4a0-4b29-bfe8-2254ab6869b3.@2751d542-2551-4327-8082-c7cb5c917379": {
			"chp": 10036,
			"id": 16,
			"text": {
				"en-us": "Business Process",
				"de-de": "Geschäftsprozess",
				"es-es": "Procesos",
				"fr-fr": "Processus",
				"it-it": "Business process",
				"pt-pt": "Processo de negócio"
			},
			"$key": "37358D7111D9D1330166947EFD3EB1D657B085DC"
		},
		"pageLayout.d0943dfb-f070-4e0a-bac2-8be4968fa285.@b7418641-8d0d-4529-b160-de97f46d31f3": {
			"chp": 10036,
			"id": 17,
			"text": {
				"en-us": "Key Information",
				"de-de": "Schlüsselinformationen",
				"es-es": "Indicadores",
				"fr-fr": "Indicateurs",
				"it-it": "Informazioni chiave",
				"pt-pt": "Informação chave"
			},
			"$key": "F6D967B5886598BE6B26B84D7687CEFAB441DB7E"
		},
		"pageLayout.d0943dfb-f070-4e0a-bac2-8be4968fa285.@8fba941c-7bc9-4e7e-9203-daeae79ce4d0": {
			"chp": 10036,
			"id": 18,
			"text": {
				"en-us": "Business Process",
				"de-de": "Geschäftsprozess",
				"es-es": "Procesos",
				"fr-fr": "Processus",
				"it-it": "Business process",
				"pt-pt": "Processo de negócio"
			},
			"$key": "9467577E228791DA05AD846D055E3D9D15290187"
		},
		"pageLayout.83df2eef-f26b-4881-9335-4c236d3f47b3.@f0a37609-be98-4353-bc60-c9a1953c7d10": {
			"chp": 10036,
			"id": 19,
			"text": {
				"en-us": "Key Information",
				"de-de": "Schlüsselinformationen",
				"es-es": "Indicadores",
				"fr-fr": "Indicateurs",
				"it-it": "Informazioni chiave",
				"pt-pt": "Informação chave"
			},
			"$key": "6C74FD026C847A5EFFAE81683CD8D4621270B3CB"
		},
		"pageLayout.83df2eef-f26b-4881-9335-4c236d3f47b3.@1c2f4697-4042-43b3-b984-7a08c08b1933": {
			"chp": 10036,
			"id": 20,
			"text": {
				"en-us": "Business Process",
				"de-de": "Geschäftsprozess",
				"es-es": "Procesos",
				"fr-fr": "Processus",
				"it-it": "Business process",
				"pt-pt": "Processo de negócio"
			},
			"$key": "C61FC42F57F0C609A51CCE98BB7E6E3B26B63504"
		},
		"pageLayout.729659d5-d9a8-4efb-a7de-b75e22866d59.@6805a136-be51-455c-a2b9-93f6acd6a9e4": {
			"chp": 10036,
			"id": 21,
			"text": {
				"en-us": "Key Information",
				"de-de": "Schlüsselinformationen",
				"es-es": "Indicadores",
				"fr-fr": "Indicateurs",
				"it-it": "Informazioni chiave",
				"pt-pt": "Informação chave"
			},
			"$key": "119061C091B80EAB5E7D42FD4E5A5D23C8251020"
		},
		"pageLayout.729659d5-d9a8-4efb-a7de-b75e22866d59.@7ea52985-5f73-4331-a58c-6a8e86988cf8": {
			"chp": 10036,
			"id": 22,
			"text": {
				"en-us": "Business Process",
				"de-de": "Geschäftsprozess",
				"es-es": "Procesos",
				"fr-fr": "Processus",
				"it-it": "Business process",
				"pt-pt": "Processo de negócio"
			},
			"$key": "44A08372F96684AD1302EF47B0B6E2165CA84112"
		},
		"pageLayout.c9ff28f5-4412-4a01-87a9-d95bbaac7907.@cb1b5b4d-4b36-4ac1-9827-5ef50db4b0c5": {
			"chp": 10036,
			"id": 23,
			"text": {
				"en-us": "Key Information",
				"fr-fr": "Indicateurs"
			},
			"$key": "E149DD6F0B01AC29ACCED5C7DDDF98B3C9BC8081"
		},
		"pageLayout.c9ff28f5-4412-4a01-87a9-d95bbaac7907.@8472fa57-d588-4926-8ad2-25296e9424a9": {
			"chp": 10036,
			"id": 24,
			"text": {
				"en-us": "Business Process",
				"fr-fr": "Processus"
			},
			"$key": "DF5B61A6A9F34C7DE482053EF889BCDBBA23FDF5"
		},
		"pageLayout.37b474e5-e6c7-485a-9737-547fc5361cd0.@2348c43c-a7f9-4751-bb9e-a94c77c86f0e": {
			"chp": 10036,
			"id": 25,
			"text": {
				"en-us": "Quote",
				"de-de": "Angebote",
				"es-es": "Presupuestos",
				"fr-fr": "Devis"
			},
			"$key": "BA2AD90CBBB66B090DB963EAA60BA2BAEE0D75BD"
		},
		"pageLayout.37b474e5-e6c7-485a-9737-547fc5361cd0.@593c47fe-64f2-4c8f-a4a5-54fd342fe4c9": {
			"chp": 10036,
			"id": 26,
			"text": {
				"en-us": "Order",
				"de-de": "Aufträge",
				"es-es": "Pedidos",
				"fr-fr": "Commandes"
			},
			"$key": "567086ACAA5D8FC48CD4A9E18BE24DECE65CA848"
		},
		"pageLayout.37b474e5-e6c7-485a-9737-547fc5361cd0.@cd61b9fc-25ed-4165-b2c1-163c616d0d6f": {
			"chp": 10036,
			"id": 27,
			"text": {
				"en-us": "Open order",
				"de-de": "Offene Aufträge",
				"es-es": "Pedidos",
				"fr-fr": "Commandes ouvertes"
			},
			"$key": "C0EFFF30BFA37BAB91808B17DC0634A0B3EE8D8F"
		},
		"pageLayout.37b474e5-e6c7-485a-9737-547fc5361cd0.@669b21d8-8747-48c9-8915-616512190c58": {
			"chp": 10036,
			"id": 28,
			"text": {
				"en-us": "Historical",
				"de-de": "Historische",
				"es-es": "Histórico",
				"fr-fr": "Historique"
			},
			"$key": "7E820C84F6852E179E8FEEA1391223A8BFC3BC59"
		},
		"pageLayout.6e079068-fca7-4bb1-b33a-cbb48c2b7446.@55e942fe-cfe5-495c-8e39-1b1f60de6056": {
			"chp": 10036,
			"id": 29,
			"text": {
				"en-us": "Purchase request",
				"de-de": "Bestellanfragen",
				"es-es": "Solicitudes de compra",
				"fr-fr": "Demandes d'achats"
			},
			"$key": "2C499569BDA9FF527E92E1FF0B8EAC268E8B329A"
		},
		"pageLayout.6e079068-fca7-4bb1-b33a-cbb48c2b7446.@87faa6f5-b357-4dea-a4dd-e3931c2109ac": {
			"chp": 10036,
			"id": 30,
			"text": {
				"en-us": "Order",
				"de-de": "Bestellungen",
				"es-es": "Pedidos",
				"fr-fr": "Commandes"
			},
			"$key": "1B84187E965E73EC545D117B9B894BD9E2021E30"
		},
		"pageLayout.6e079068-fca7-4bb1-b33a-cbb48c2b7446.@8285bf6a-520a-4add-ae5a-daa0a83eb8a3": {
			"chp": 10036,
			"id": 31,
			"text": {
				"en-us": "Open order",
				"de-de": "Offene Bestellungen",
				"es-es": "Pedidos abiertos",
				"fr-fr": "Commandes ouvertes"
			},
			"$key": "2F66604A56F66425106905A986C0BB17E24C1BED"
		},
		"pageLayout.ac80f86e-6efa-4d6a-8205-ad7f424c1f94.@1e6bc3b3-62ad-4738-95a0-fda4cc3958e1": {
			"chp": 10036,
			"id": 32,
			"text": {
				"en-us": "New Tab 1"
			},
			"$key": "D3972D5B78BD0BB7E3B14FE546F4B0D4995BC4F6"
		},
		"pageLayout.92edd203-b74b-42a1-9dea-a76d56f2afb1.@62d17e43-4e1c-486b-9f8d-b5478bf32303": {
			"chp": 10036,
			"id": 33,
			"text": {
				"en-us": "Key Information",
				"fr-fr": "Indicateurs"
			},
			"$key": "CC455B286A2EAA488C0C87B4ADDD23332B76588C"
		},
		"pageLayout.92edd203-b74b-42a1-9dea-a76d56f2afb1.@e2c94202-e24a-4fa3-bdf8-419ba276dc0a": {
			"chp": 10036,
			"id": 34,
			"text": {
				"en-us": "Business Process",
				"fr-fr": "Processus"
			},
			"$key": "B43E8D642F93311102BF3CFD26258324AECD361B"
		},
		"pageLayout.65bc85ae-a95a-43ff-8705-e909604030e0.@d3d15e0c-868c-4bc1-8e72-110f96bf1e57": {
			"chp": 10036,
			"id": 35,
			"text": {
				"en-us": "Key Information",
				"fr-fr": "Indicateurs"
			},
			"$key": "95DF9BE99C109997D66761428083826BFBCA1759"
		},
		"pageLayout.bc11fa84-bc56-4cf9-abd6-c75247f8b56e.@e3d61be9-6c02-4efa-992f-1f0ecd1ef60f": {
			"chp": 10036,
			"id": 36,
			"text": {
				"en-us": "Key Information",
				"fr-fr": "Indicateurs"
			},
			"$key": "78988A0BB87A4143368A331DA442BFC26FA13250"
		},
		"pageLayout.bc11fa84-bc56-4cf9-abd6-c75247f8b56e.@d37e4fe3-43ab-4322-a39b-9842d41c9828": {
			"chp": 10036,
			"id": 37,
			"text": {
				"en-us": "Business Process",
				"fr-fr": "Processus"
			},
			"$key": "BB9219828B9AE108B2A731A6B0743B9566FB03E4"
		},
		"pageLayout.b7541149-c301-4aee-bd5c-5b8ddc2423cb.@d6d02324-ba11-4d09-ab48-83e812171b32": {
			"chp": 10036,
			"id": 38,
			"text": {
				"en-us": "Key Information",
				"fr-fr": "Indicateurs"
			},
			"$key": "C2CE1689AA312552687ABDE8BDD29A7E69F63743"
		},
		"pageLayout.b7541149-c301-4aee-bd5c-5b8ddc2423cb.@dd2da1cd-482d-45b3-8654-b57f138b3f4f": {
			"chp": 10036,
			"id": 39,
			"text": {
				"en-us": "Business Process",
				"fr-fr": "Processus"
			},
			"$key": "E7E3779C440EE349D86033B4B64E697167928960"
		},
		"pageLayout.79e2d150-5866-42f9-bbb3-7f07b369b92c.@a6bb7393-cbc0-4642-9d3a-d14560b78016": {
			"chp": 10036,
			"id": 40,
			"text": {
				"en-us": "Key Information",
				"fr-fr": "Indicateurs"
			},
			"$key": "49A3D8652F356C794D65ECD284B7A46AF853BA59"
		},
		"pageLayout.79e2d150-5866-42f9-bbb3-7f07b369b92c.@6d3dc437-77e8-4b8a-87ac-dffbcc864aab": {
			"chp": 10036,
			"id": 41,
			"text": {
				"en-us": "Business Process",
				"fr-fr": "Processus"
			},
			"$key": "81BBB266C82BC5F23EC75C0D8F518216C3C07DF4"
		},
		"pageLayout.8ce38a84-8692-4409-abe7-75345aa8999a.@50d07c96-e55e-4a8c-8e76-247d0a9614d3": {
			"chp": 10036,
			"id": 42,
			"text": {
				"en-us": "Already using Sage ERP X3 ?"
			},
			"$key": "0246AFCF8D968FC3FDB121C3C0BC28877223E67D"
		},
		"pageLayout.a1a251b4-684f-48bb-a0ff-5817d84baa72.@656afa2f-1f3c-4fb0-9c41-324817cd6869": {
			"chp": 10036,
			"id": 43,
			"text": {
				"en-us": "Key Information",
				"de-de": "Schlüsselinformationen",
				"es-es": "Indicadores",
				"fr-fr": "Indicateurs",
				"it-it": "Informazioni chiave",
				"pt-pt": "Informação chave"
			},
			"$key": "D6072991669DA9A3B90E9E3E56B229B2CEBBEDBB"
		},
		"pageLayout.a1a251b4-684f-48bb-a0ff-5817d84baa72.@383ad414-ba09-44f1-9c1c-d2c627c2c4b0": {
			"chp": 10036,
			"id": 44,
			"text": {
				"en-us": "Business Process",
				"fr-fr": "Processus"
			},
			"$key": "5CCABED6E412CDFAD0F868BA55DB4F76BEBB1000"
		},
		"pageLayout.a1a251b4-684f-48bb-a0ff-5817d84baa72.@7685b672-b965-4ddb-961f-78a745757d9c": {
			"chp": 10036,
			"id": 45,
			"text": {
				"en-us": "Business processes",
				"de-de": "Geschäftsprozess",
				"es-es": "Procesos",
				"fr-fr": "Processus",
				"it-it": "Business process",
				"pt-pt": "Processo de negócio"
			},
			"$key": "E27E415E2E9379D5401BDB3CCF1FDB11F01565B4"
		},
		"pageLayout.2ec3b413-3748-4976-8f92-c35f945b8e17.@12aadb27-6d89-4530-b4bb-448525695a8e": {
			"chp": 10036,
			"id": 46,
			"text": {
				"en-us": "Key Information",
				"de-de": "Schlüsselinformationen",
				"es-es": "Indicadores",
				"fr-fr": "Indicateurs",
				"it-it": "Informazioni chiave",
				"pt-pt": "Informação chave"
			},
			"$key": "E6E78F8E53E0E19B1EE1C54276AA6E491B37DD3E"
		},
		"pageLayout.2ec3b413-3748-4976-8f92-c35f945b8e17.@992825f7-4df4-43bf-b4f6-d844140a2e2e": {
			"chp": 10036,
			"id": 47,
			"text": {
				"en-us": "Business Process",
				"de-de": "Geschäftsprozess",
				"es-es": "Procesos",
				"fr-fr": "Processus",
				"it-it": "Business process",
				"pt-pt": "Processo de negócio"
			},
			"$key": "7EAF56D8D81193C7E8254FB317822EBBBE5F8E2B"
		},
		"pageLayout.719d627f-7ed0-4651-8dcf-db9c7b28448e.@67a2899f-b774-4bc0-bac3-fb899aafca51": {
			"chp": 10036,
			"id": 48,
			"text": {
				"en-us": "Key Information",
				"fr-fr": "Indicateurs"
			},
			"$key": "98D472FD971DE3B325C74BA221266170F0FF000D"
		},
		"pageLayout.719d627f-7ed0-4651-8dcf-db9c7b28448e.@c0d19673-ac03-427f-af67-0d03cb2db466": {
			"chp": 10036,
			"id": 49,
			"text": {
				"en-us": "Business Process",
				"fr-fr": "Processus"
			},
			"$key": "A474FE37E1BF6CB2800ABA1298EF43E7CF41ED83"
		},
		"pageLayout.719d627f-7ed0-4651-8dcf-db9c7b28448e.@35a4d8bd-d993-4fd2-90a5-166025620662": {
			"chp": 10036,
			"id": 50,
			"text": {
				"en-us": "Business process",
				"fr-fr": "Processus"
			},
			"$key": "A2AAD102B6DE3E9FE7CED7EED92878C772B03FBF"
		},
		"pageLayout.5f6d3af1-5937-4f37-95cb-c791845aa1cd.@3b2623ec-889d-4cf0-9d8a-a8a77dad855f": {
			"chp": 10036,
			"id": 51,
			"text": {
				"en-us": "Automation & Visibility"
			},
			"$key": "43EB95DFE09FB77B86C4C0A5DC898F90E7A8F268"
		},
		"pageLayout.5f6d3af1-5937-4f37-95cb-c791845aa1cd.@2df7709c-23ef-4ccb-9661-34eb01243b9d": {
			"chp": 10036,
			"id": 52,
			"text": {
				"en-us": "Warehouse Manager"
			},
			"$key": "693A64759E3F6073CBFD5172332EC84520EBD481"
		},
		"pageLayout.5f6d3af1-5937-4f37-95cb-c791845aa1cd.@dfafe7fc-3b17-4045-94bb-fb1cce780d4e": {
			"chp": 10036,
			"id": 53,
			"text": {
				"en-us": "Sales Manager"
			},
			"$key": "1E95403A21A9A11653E3D665C3E2EE42ED8D7743"
		},
		"pageLayout.5f6d3af1-5937-4f37-95cb-c791845aa1cd.@10a7c863-9240-4e99-a812-5e5b49aead3c": {
			"chp": 10036,
			"id": 54,
			"text": {
				"en-us": "Debtors Administrator"
			},
			"$key": "51B7EBE04D5FC56E8AA913A927465C5A4ECF737C"
		},
		"pageLayout.5f6d3af1-5937-4f37-95cb-c791845aa1cd.@c4c150ab-7f55-4865-9546-e3ce6744abca": {
			"chp": 10036,
			"id": 55,
			"text": {
				"en-us": "Visibility"
			},
			"$key": "ED6B4C04BAD4E36A7770024890C9B81303FDD283"
		},
		"pageLayout.5f6d3af1-5937-4f37-95cb-c791845aa1cd.@99082998-dcbc-4885-aec4-e06a6b67c1db": {
			"chp": 10036,
			"id": 56,
			"text": {
				"en-us": "Introduction"
			},
			"$key": "00B46575FA1A148EFA66199D839E475569A4FAA0"
		},
		"pageLayout.5f6d3af1-5937-4f37-95cb-c791845aa1cd.@9807555c-de82-4edf-989b-e3fb7a213768": {
			"chp": 10036,
			"id": 57,
			"text": {
				"en-us": "Automation & Visibility"
			},
			"$key": "BF5EEAA98BE78CA0BDC406FDB2CE0722A7E5B41E"
		},
		"pageLayout.5f6d3af1-5937-4f37-95cb-c791845aa1cd.@16685eab-520a-4f47-aee1-cf92b2413a7a": {
			"chp": 10036,
			"id": 58,
			"text": {
				"en-us": "Automation & Visibility"
			},
			"$key": "2E2DD7226AFBB676A9147A326E6AE2D60CD95F36"
		},
		"pageLayout.5f6d3af1-5937-4f37-95cb-c791845aa1cd.@70e14fd0-d494-4af8-9e6c-6ecd75fa30d1": {
			"chp": 10036,
			"id": 59,
			"text": {
				"en-us": "Warehouse Manager"
			},
			"$key": "0D3CD65DAD0C6FB683B4727305606E6B4D69A9C1"
		},
		"pageLayout.5f6d3af1-5937-4f37-95cb-c791845aa1cd.@fd561aee-7cd1-4351-a020-e52cc43c08c5": {
			"chp": 10036,
			"id": 60,
			"text": {
				"en-us": "Sales Manager"
			},
			"$key": "CABB59FDFFFFA16E5CE8C192021BA0EF9AFA5CB9"
		},
		"pageLayout.5f6d3af1-5937-4f37-95cb-c791845aa1cd.@4bae0b93-2645-482a-937a-7670b934b312": {
			"chp": 10036,
			"id": 61,
			"text": {
				"en-us": "Sales Manager"
			},
			"$key": "60D276F7FACC747997F8BF4AC0A69967B7E2DEAA"
		},
		"pageLayout.5f6d3af1-5937-4f37-95cb-c791845aa1cd.@7ec774b2-b8cb-4453-bab5-c1233e18173d": {
			"chp": 10036,
			"id": 62,
			"text": {
				"en-us": "New Tab 1"
			},
			"$key": "09BCE0A873193301EECD6CE95CBDABD95F487022"
		},
		"pageLayout.5f6d3af1-5937-4f37-95cb-c791845aa1cd.@89f71c79-fb40-4a08-9924-bf8bf2f2d15f": {
			"chp": 10036,
			"id": 63,
			"text": {
				"en-us": "Debtors Administrator"
			},
			"$key": "582F7A6D727041A266CEC65A682DFFF95B86CB7B"
		},
		"pageLayout.5f6d3af1-5937-4f37-95cb-c791845aa1cd.@adf391a3-1063-4be5-8b78-f1cb32de3b30": {
			"chp": 10036,
			"id": 64,
			"text": {
				"en-us": "Automation & Visibility"
			},
			"$key": "EBFF9E4AC058CDD9558F59F2A09371922F8F2239"
		},
		"pageLayout.5f6d3af1-5937-4f37-95cb-c791845aa1cd.@4cebba3d-8a72-4e95-8525-ea427fae3eb3": {
			"chp": 10036,
			"id": 65,
			"text": {
				"en-us": "Automation & Visibility"
			},
			"$key": "654EE61F305AD51CBA1F59254F2AF2F2403546D3"
		},
		"pageLayout.5f6d3af1-5937-4f37-95cb-c791845aa1cd.@83303f69-4a5d-4bb7-8768-a22bee6058df": {
			"chp": 10036,
			"id": 66,
			"text": {
				"en-us": "Warehouse Manager"
			},
			"$key": "F7231F0056103388DACB6FEE289C4EB6AB35351A"
		},
		"pageLayout.5f6d3af1-5937-4f37-95cb-c791845aa1cd.@168f500c-aed6-4720-8695-3cee8427bb85": {
			"chp": 10036,
			"id": 67,
			"text": {
				"en-us": "Sales Manager"
			},
			"$key": "B7C415C59779A1F75134C4BEF8D17E6A38CE16E4"
		},
		"pageLayout.5f6d3af1-5937-4f37-95cb-c791845aa1cd.@7357f69c-15f2-4ead-9cab-90ecc6604ff2": {
			"chp": 10036,
			"id": 68,
			"text": {
				"en-us": "Debtors Administrator"
			},
			"$key": "0C15A2EB9DAB36E641738D4A530EE1E7ACD7B696"
		},
		"pageLayout.5f6d3af1-5937-4f37-95cb-c791845aa1cd.@53b8d4ad-a7e4-40d6-804a-6b4484bc4ba3": {
			"chp": 10036,
			"id": 69,
			"text": {
				"en-us": "Warehouse Manager"
			},
			"$key": "E4539F0A76AD47648B531FD134E43039C9179FF0"
		},
		"pageLayout.7f7fe692-c00c-4cf4-b215-41a4fe1a638c.@2b036869-40b8-4c2a-b594-63eb68c9e9db": {
			"chp": 10036,
			"id": 70,
			"text": {
				"en-us": "Expansion"
			},
			"$key": "C8DE36C3578B07D540AE82DCD6FCFFADE10CC604"
		},
		"pageLayout.7f7fe692-c00c-4cf4-b215-41a4fe1a638c.@6e3b2cb6-89b2-4993-ad7d-79a08ab99149": {
			"chp": 10036,
			"id": 71,
			"text": {
				"en-us": "Overview"
			},
			"$key": "D586CCF5EE5228396491375FC73AA9CDF9DDF100"
		},
		"pageLayout.7f7fe692-c00c-4cf4-b215-41a4fe1a638c.@1aa2bc82-ee02-48a8-8a75-34653e42cd0e": {
			"chp": 10036,
			"id": 72,
			"text": {
				"en-us": "Financial Organization"
			},
			"$key": "D8232F38FE0BD502121FBB4BBE76675CD72B35DF"
		},
		"pageLayout.7f7fe692-c00c-4cf4-b215-41a4fe1a638c.@9870cfa8-e25e-4b89-801b-b787b20e230f": {
			"chp": 10036,
			"id": 73,
			"text": {
				"en-us": "Financial Managment"
			},
			"$key": "F3DE07EE0602A56E7AF4579746BDC65039C93367"
		},
		"pageLayout.7f7fe692-c00c-4cf4-b215-41a4fe1a638c.@ea20dce7-5ce0-4680-84d7-12e756662bfa": {
			"chp": 10036,
			"id": 74,
			"text": {
				"en-us": "Test",
				"en-gb": "New Tab 1"
			},
			"$key": "247BBB444A4F17E6E7D94AEDC5EA7B33022F0E55"
		},
		"pageLayout.7f7fe692-c00c-4cf4-b215-41a4fe1a638c.@15a926ed-9b19-4349-a1fa-976d9dd9905e": {
			"chp": 10036,
			"id": 75,
			"text": {
				"en-us": "New Tab 1"
			},
			"$key": "8BB4119B7248B3F12B7F94B96D60AFB1346D259A"
		},
		"pageLayout.7f7fe692-c00c-4cf4-b215-41a4fe1a638c.@e0693c7e-4084-46cd-a96a-dd7e98600169": {
			"chp": 10036,
			"id": 76,
			"text": {
				"en-us": "Expansion"
			},
			"$key": "A901D926B561BA66629F9905E790132CA74FDB9A"
		},
		"pageLayout.7f7fe692-c00c-4cf4-b215-41a4fe1a638c.@bd71a157-5880-453a-a313-98214654e336": {
			"chp": 10036,
			"id": 77,
			"text": {
				"en-us": "Expansion"
			},
			"$key": "A62B5025604CABBC0591D57093020D877F3C762D"
		},
		"pageLayout.7f7fe692-c00c-4cf4-b215-41a4fe1a638c.@18e75b45-4824-452c-ac50-da15aa15fd22": {
			"chp": 10036,
			"id": 78,
			"text": {
				"en-us": "New Tab 1"
			},
			"$key": "CE38392A9DF54DCEC55E1307B01A5FA4EEFB3F02"
		},
		"pageLayout.7f7fe692-c00c-4cf4-b215-41a4fe1a638c.@de1f76e6-95e6-4d31-9775-a8ea193cae40": {
			"chp": 10036,
			"id": 79,
			"text": {
				"en-us": "Expansion Metrics"
			},
			"$key": "43ABDC95ADD1BD3AD70883FA64DBFB81FC5848AE"
		},
		"pageLayout.7f7fe692-c00c-4cf4-b215-41a4fe1a638c.@409d5dc3-9bb1-490e-9348-1356ff0da7bb": {
			"chp": 10036,
			"id": 80,
			"text": {
				"en-us": "Scale and expand"
			},
			"$key": "61446D4950B4AA814B80912C3A40207940E422BB"
		},
		"pageLayout.7f7fe692-c00c-4cf4-b215-41a4fe1a638c.@ded6b4de-41f9-4d52-9d23-6466b628da71": {
			"chp": 10036,
			"id": 81,
			"text": {
				"en-us": "Expansion Metrics"
			},
			"$key": "074A6E95611977E92DDAA9B2A03709728D45224A"
		},
		"pageLayout.7f7fe692-c00c-4cf4-b215-41a4fe1a638c.@bd117d6d-f604-4ccd-94e8-d21d74cf7652": {
			"chp": 10036,
			"id": 82,
			"text": {
				"en-us": "New Tab 1"
			},
			"$key": "A25219DE37F2267DF76CA25803B2B6A20D09BD3B"
		},
		"pageLayout.87657209-b425-4582-8cf5-5cbf67b41bf1.@25e64751-1929-4661-998f-a756c2261673": {
			"chp": 10036,
			"id": 83,
			"text": {
				"en-us": "New Tab 1"
			},
			"$key": "1A9E54753902292E4C521D66F1D8B8B149BCA6F6"
		},
		"pageLayout.87657209-b425-4582-8cf5-5cbf67b41bf1.@bb3e7e59-7e8b-4eaa-954c-77d5d904c3ac": {
			"chp": 10036,
			"id": 84,
			"text": {
				"en-us": "Go where you Business takes you"
			},
			"$key": "37E391AA9BDA23A66BFF9BA72169CDBA336910B9"
		},
		"pageLayout.87657209-b425-4582-8cf5-5cbf67b41bf1.@2ca0bcbc-bd11-4dbc-aadf-6ce819631e45": {
			"chp": 10036,
			"id": 85,
			"text": {
				"en-us": "Mobility"
			},
			"$key": "169C185814050BCFB86A5D7BFBDF299FBA39B1FE"
		},
		"pageLayout.87657209-b425-4582-8cf5-5cbf67b41bf1.@b7f1a541-cc1c-4213-bee4-c0b6ccdab9be": {
			"chp": 10036,
			"id": 86,
			"text": {
				"en-us": "My quick view"
			},
			"$key": "18D5DF66AAA5F579162B42317B9760A5E9FC99E1"
		},
		"pageLayout.87657209-b425-4582-8cf5-5cbf67b41bf1.@d6cc1002-292d-480c-95b1-bf22dd59918e": {
			"chp": 10036,
			"id": 87,
			"text": {
				"en-us": "My quick view"
			},
			"$key": "4586AFBCA45C7BC4599740C84B4A0F4A41600819"
		},
		"pageLayout.87657209-b425-4582-8cf5-5cbf67b41bf1.@17947a19-4a92-4fe7-818f-81f8c9f5430f": {
			"chp": 10036,
			"id": 88,
			"text": {
				"en-us": "New Tab 1"
			},
			"$key": "F88251E9F4F8E16BF9035CB9552247000DEBE633"
		},
		"pageLayout.db0a9dc6-b5d5-4278-8f51-ee99043df2b0.@27a8765d-19e3-4996-961b-cd9841602500": {
			"chp": 10036,
			"id": 89,
			"text": {
				"en-us": "KPIs"
			},
			"$key": "9805ED6D0E781C238D50F351CA67F00EF071A525"
		},
		"pageLayout.db0a9dc6-b5d5-4278-8f51-ee99043df2b0.@9c72c975-1248-4924-bbcc-0f40de28e9dd": {
			"chp": 10036,
			"id": 90,
			"text": {
				"en-us": "KPIs"
			},
			"$key": "2521F43395268438C4DA45E71109FFDA9C2619CA"
		},
		"pageLayout.db0a9dc6-b5d5-4278-8f51-ee99043df2b0.@ccfb2d13-197e-4387-b63d-7b5268212131": {
			"chp": 10036,
			"id": 91,
			"text": {
				"en-us": "Processing"
			},
			"$key": "1721A15A86835B69914E08B9D709AAA173B68D8C"
		},
		"pageLayout.db0a9dc6-b5d5-4278-8f51-ee99043df2b0.@fc2e6d82-111c-42b7-984f-cf3304833272": {
			"chp": 10036,
			"id": 92,
			"text": {
				"en-us": "New Tab 1"
			},
			"$key": "42E85ADE45A60D97514257D5B1112DD3C24C2382"
		},
		"pageLayout.9906abe4-1449-4b6b-9d6c-78caf30b6171.@347467df-e457-4a72-ab96-694394246897": {
			"chp": 10036,
			"id": 93,
			"text": {
				"en-us": "Serve your customers better"
			},
			"$key": "CA0ECC92F0A24859255815197CF048FBFD9EFF5F"
		},
		"pageLayout.7f953818-a95e-4a2d-a72a-bb4bf2fae033.@799aeec1-fa65-4e02-9172-a4444e72a5ea": {
			"chp": 10036,
			"id": 94,
			"text": {
				"en-us": "Create cash flow"
			},
			"$key": "3392B352E4C2564980B213E85D39C899DAD899B7"
		},
		"pageLayout.fd67a248-fcd0-40e0-a094-0f453bd036de.@25e64751-1929-4661-998f-a756c2261673": {
			"chp": 10036,
			"id": 95,
			"text": {
				"en-us": "New Tab 1"
			},
			"$key": "A491391EFEE9F636E08F184A755F207282B70EC5"
		},
		"pageLayout.fd67a248-fcd0-40e0-a094-0f453bd036de.@bb3e7e59-7e8b-4eaa-954c-77d5d904c3ac": {
			"chp": 10036,
			"id": 96,
			"text": {
				"en-us": "Go where you Business takes you"
			},
			"$key": "B457B8582ABB455D135DCEDF201D73BC03802584"
		},
		"pageLayout.fd67a248-fcd0-40e0-a094-0f453bd036de.@2ca0bcbc-bd11-4dbc-aadf-6ce819631e45": {
			"chp": 10036,
			"id": 97,
			"text": {
				"en-us": "Mobility"
			},
			"$key": "D708B92DFD5AB49527DDBD079CBEEE1422BEEC08"
		},
		"pageLayout.fd67a248-fcd0-40e0-a094-0f453bd036de.@b7f1a541-cc1c-4213-bee4-c0b6ccdab9be": {
			"chp": 10036,
			"id": 98,
			"text": {
				"en-us": "My quick view"
			},
			"$key": "16D562BF77AF33AC4E37BE1E0CDC2D119D239B83"
		},
		"pageLayout.fd67a248-fcd0-40e0-a094-0f453bd036de.@d6cc1002-292d-480c-95b1-bf22dd59918e": {
			"chp": 10036,
			"id": 99,
			"text": {
				"en-us": "My quick view"
			},
			"$key": "05EE1396F3751C8775B12C7810ACECBD96CDC764"
		},
		"pageLayout.fd67a248-fcd0-40e0-a094-0f453bd036de.@c3c150b0-46f4-4bd4-9a07-353bae08c842": {
			"chp": 10036,
			"id": 100,
			"text": {
				"en-us": "mY TEST"
			},
			"$key": "137F438F1FE80287C6DF3507F7584A0B8AB63B8A"
		},
		"pageLayout.fd67a248-fcd0-40e0-a094-0f453bd036de.@5cae9303-a2fa-47db-887a-a78c515548c6": {
			"chp": 10036,
			"id": 101,
			"text": {
				"en-us": "New Tab 1"
			},
			"$key": "1A625F84290A993168E87255F1CCD0A1B26235C6"
		},
		"pageLayout.fd67a248-fcd0-40e0-a094-0f453bd036de.@f7fa4edc-2a80-4dc8-b6ef-15abc0ccad6e": {
			"chp": 10036,
			"id": 102,
			"text": {
				"en-us": "New Tab 1"
			},
			"$key": "B799FD18DA6A0E23BF619B3127141FA912C3975C"
		},
		"pageLayout.fd67a248-fcd0-40e0-a094-0f453bd036de.@3258beb4-3c3d-492a-b4a6-59c9a4e76b59": {
			"chp": 10036,
			"id": 103,
			"text": {
				"en-us": "New Tab 2"
			},
			"$key": "D5C9F30C9B9C5625CD6DA0EF3E5562AA3D316AE7"
		},
		"pageLayout.c8fa89f9-82db-4c11-b869-848b8dfaab3c.@3c25a712-aede-4e70-9837-c1545df26c7a": {
			"chp": 10036,
			"id": 104,
			"text": {
				"en-us": "New Tab 1"
			},
			"$key": "8B138C44DAE7F4EC3DBFF4572322FFF4FBD71751"
		},
		"pageLayout.c8fa89f9-82db-4c11-b869-848b8dfaab3c.@a6ee2c31-bba9-4c80-82b9-ade500e1ab4b": {
			"chp": 10036,
			"id": 105,
			"text": {
				"en-us": "Visual Process"
			},
			"$key": "19F1D5586ACAE64DD9CEA2EB1BE83C778E2580AA"
		},
		"pageLayout.c8fa89f9-82db-4c11-b869-848b8dfaab3c.@ed82c832-31a6-4a3a-a486-f11345760a3e": {
			"chp": 10036,
			"id": 106,
			"text": {
				"en-us": "New Tab 1"
			},
			"$key": "C0C3628C691CCCAAFEC9CFBA8A8AE5D3C37AF043"
		},
		"pageLayout.c8fa89f9-82db-4c11-b869-848b8dfaab3c.@e64c9d4d-fc06-4e0d-9b9e-b1eed24d0735": {
			"chp": 10036,
			"id": 107,
			"text": {
				"en-us": "Intranet"
			},
			"$key": "A387AE40BA97BAEB2338CBBD419714979CA0AC80"
		},
		"pageLayout.c8fa89f9-82db-4c11-b869-848b8dfaab3c.@34c77bd3-5b9b-441e-af3b-f98704468f76": {
			"chp": 10036,
			"id": 108,
			"text": {
				"en-us": "Indicators"
			},
			"$key": "C4F63C0A495549E666A05EAFA2C71A376E09C6F8"
		},
		"pageLayout.c8fa89f9-82db-4c11-b869-848b8dfaab3c.@755ffc4c-ee5d-4746-80be-97b528adab25": {
			"chp": 10036,
			"id": 109,
			"text": {
				"en-us": "New Tab 1"
			},
			"$key": "7294F47209B3F7F4D8D713BA5291FDC5FD325DEA"
		},
		"pageLayout.c8fa89f9-82db-4c11-b869-848b8dfaab3c.@ba08a758-6413-4c4c-a521-84083019e181": {
			"chp": 10036,
			"id": 110,
			"text": {
				"en-us": "New Tab 2"
			},
			"$key": "B237AB45278F37DE9DC0928E0AA5158E42470CB9"
		},
		"pageLayout.300bc661-38ec-48d7-824c-bcca7dc35fe0.@af8d6dc7-96ab-43de-bff5-7b8c23678359": {
			"chp": 10036,
			"id": 111,
			"text": {
				"en-us": "Key Information",
				"fr-fr": "Indicateurs"
			},
			"$key": "7A17828149B91BB13E3EA3A604A77BE1363C3AA1"
		},
		"pageLayout.300bc661-38ec-48d7-824c-bcca7dc35fe0.@2cd495f8-163b-4001-aec0-4e9a9382aba3": {
			"chp": 10036,
			"id": 112,
			"text": {
				"en-us": "Business Process",
				"fr-fr": "Processus"
			},
			"$key": "970454DC12A4FE1016E39C741F8F5B04C7AAE639"
		},
		"pageLayout.e4eb4671-d879-47f6-ae9a-896cc6f1d4f9.@74f5d1a3-cb35-4f71-91ab-3a60ef982cd6": {
			"chp": 10036,
			"id": 113,
			"text": {
				"en-us": "Business Process",
				"fr-fr": "Processus"
			},
			"$key": "766F22F8BBEE4AC76BEFC1CB83F766050805CC04"
		},
		"pageLayout.ab3bf9e2-510e-498f-becc-3ed3777633cc.@9468b05c-3bf4-45c4-b602-c1789f10ebdd": {
			"chp": 10036,
			"id": 114,
			"text": {
				"en-us": "Key Information",
				"fr-fr": "Indicateurs"
			},
			"$key": "A3EBE8BE11F36596BB17C49D360E7D33BD032B27"
		},
		"pageLayout.ab3bf9e2-510e-498f-becc-3ed3777633cc.@7324c280-6ee0-4827-99f0-bf0fdb2e8f2b": {
			"chp": 10036,
			"id": 115,
			"text": {
				"en-us": "Business Process",
				"fr-fr": "Processus"
			},
			"$key": "BB4DAD526DB492CB057437344C376C1FE0CC2D4B"
		},
		"pageLayout.5886d2ff-db71-4790-bb16-b52319e62afc.@c3fcfc4e-b861-4fae-b9be-022df73e933a": {
			"chp": 10036,
			"id": 116,
			"text": {
				"en-us": "Key Information",
				"fr-fr": "Indicateurs"
			},
			"$key": "24F0FE40FDFCFDEA17929740E6944E88A91B44AA"
		},
		"pageLayout.5886d2ff-db71-4790-bb16-b52319e62afc.@1ff995ba-72bd-49cc-8df0-a536f0f444ce": {
			"chp": 10036,
			"id": 117,
			"text": {
				"en-us": "Business Process",
				"fr-fr": "Processus"
			},
			"$key": "86EAA35B1C75E82EB6534BFB49C5810A460B6EEE"
		},
		"pageLayout.cc984c46-686c-4458-a5a5-d9ac26f7d408.@f933aa8a-9e1c-455d-8b0d-d30a5f34f41a": {
			"chp": 10036,
			"id": 118,
			"text": {
				"en-us": "Key Information",
				"fr-fr": "Indicateurs"
			},
			"$key": "C540464BEE8D5FC47371829A1116B11E9C3C290B"
		},
		"pageLayout.cc984c46-686c-4458-a5a5-d9ac26f7d408.@5677cbaf-a2a2-4f5b-8483-5c4668779466": {
			"chp": 10036,
			"id": 119,
			"text": {
				"en-us": "Business Process",
				"fr-fr": "Processus"
			},
			"$key": "0401D0169B7A56D37E54E72054CC5213F7F77659"
		},
		"pageLayout.4d66bacb-bdd6-4d46-9d62-2974a5f6dc97.@9ce752a5-571a-4a8a-99cd-e0df763f73c4": {
			"chp": 10036,
			"id": 120,
			"text": {
				"en-us": "Key Information",
				"fr-fr": "Indicateurs"
			},
			"$key": "99509D309947596D3087C15ECA03F795D1511E57"
		},
		"pageLayout.4d66bacb-bdd6-4d46-9d62-2974a5f6dc97.@3ceae23b-1eb4-4fa4-aab8-86207d48cc5e": {
			"chp": 10036,
			"id": 121,
			"text": {
				"en-us": "Business Process",
				"fr-fr": "Processus"
			},
			"$key": "A8C032832BA28745A6E861CC45239FB454B818E9"
		},
		"pageLayout.856029a5-9b1d-44b6-b78a-9b10eed5a728.@6db4557f-237e-4193-8f39-b3b03ac614f1": {
			"chp": 10036,
			"id": 122,
			"text": {
				"en-us": "Key Information",
				"fr-fr": "Indicateurs"
			},
			"$key": "2A557AEEDE82CAE684FD5B5B5E75AD647319DE8D"
		},
		"pageLayout.856029a5-9b1d-44b6-b78a-9b10eed5a728.@33214254-bbf9-4d34-9de6-f2f584ec6327": {
			"chp": 10036,
			"id": 123,
			"text": {
				"en-us": "Business Process",
				"fr-fr": "Processus"
			},
			"$key": "60AFC17287E41931A172496D1CB662F9EEF9C400"
		},
		"pageLayout.e6005690-27bf-43f4-bacc-c2561823fcc6.@50fc8548-e8f9-4f9c-8bc2-8ef432a58a26": {
			"chp": 10036,
			"id": 124,
			"text": {
				"en-us": "New Tab 1"
			},
			"$key": "CBC790A87223067469E06D56FC826F7C38D070E0"
		},
		"pageLayout.e6005690-27bf-43f4-bacc-c2561823fcc6.@89b65791-d0a5-48ed-963c-85e29718850d": {
			"chp": 10036,
			"id": 125,
			"text": {
				"en-us": "New Tab 2"
			},
			"$key": "66A8396DAFDF311090CE3E733A59A7434E86AE04"
		},
		"pageLayout.fdc08b00-333b-41d7-add2-4332e9868920.@9aba45cf-793a-4a1e-8608-8e58455b8803": {
			"chp": 10036,
			"id": 126,
			"text": {
				"en-us": "My Process"
			},
			"$key": "9B0CCE87FCA9C0A7177C20A3CFE083FC118E326F"
		},
		"pageLayout.fdc08b00-333b-41d7-add2-4332e9868920.@211b71dd-aea7-4de9-90a3-12216e72f345": {
			"chp": 10036,
			"id": 127,
			"text": {
				"en-us": "Overview"
			},
			"$key": "E3E5FF103F6EBD18C022D9A5C68955493BB8BD06"
		},
		"pageLayout.fdc08b00-333b-41d7-add2-4332e9868920.@70489fb6-1d44-4c66-b51d-ef8ea16bf040": {
			"chp": 10036,
			"id": 128,
			"text": {
				"en-us": "Landing Page"
			},
			"$key": "8B8224681EFA8D98AA4E5505DCB1DAA7C92543BD"
		},
		"pageLayout.66d8309d-e0ab-4f5a-a8bb-09f1917d74ff.@92724d61-3b4e-4100-8a5d-cb35d6d26ff3": {
			"chp": 10036,
			"id": 129,
			"text": {
				"en-us": "New Tab 1"
			},
			"$key": "29A012BC5C9CBD186C77BB9D2D5F60A3EB41E24E"
		},
		"pageLayout.b3f9c0e9-12f0-4d1a-86dd-bf589dac68bf.@3b312888-8ac8-4284-984f-804ced38c739": {
			"chp": 10036,
			"id": 130,
			"text": {
				"en-us": "Get the insight you need"
			},
			"$key": "0F55066A8C06E9A80A21E32FC48EE154497F40E1"
		},
		"pageLayout.b3f9c0e9-12f0-4d1a-86dd-bf589dac68bf.@754766b3-af86-4877-9855-b93841fb762e": {
			"chp": 10036,
			"id": 131,
			"text": {
				"en-us": "Kpis"
			},
			"$key": "40B3BA19353D09B7E1A909059CC56B3DB34CB295"
		},
		"pageLayout.8c36ed6a-17d0-48dd-a5d0-d0829fd62159.@929fbe48-7282-4222-b14a-fa4817de5833": {
			"chp": 10036,
			"id": 132,
			"text": {
				"en-us": "Business Process",
				"de-de": "Geschäftsprozess",
				"es-es": "Procesos",
				"fr-fr": "Processus",
				"it-it": "Business process",
				"pt-pt": "Processo de negócio"
			},
			"$key": "7D8A897A62DE4171FB9EAC58FD905F9EF454F305"
		},
		"pageLayout.8c36ed6a-17d0-48dd-a5d0-d0829fd62159.@f81166d0-4d1e-4700-88a3-d48cceda4832": {
			"chp": 10036,
			"id": 133,
			"text": {
				"en-us": "Key Information",
				"de-de": "Schlüsselinformationen",
				"es-es": "Indicadores",
				"fr-fr": "Indicateurs",
				"it-it": "Informazioni chiave",
				"pt-pt": "Informação chave"
			},
			"$key": "09194A7F9E2C79B7B8F0599BCA7D46769F0D5C7E"
		},
		"pageLayout.e4cd4586-4ddd-4fb9-8b03-5b5783068390.@ac4324bf-a3df-4834-912e-043fe58abdef": {
			"chp": 10036,
			"id": 134,
			"text": {
				"en-us": "Key Information",
				"fr-fr": "Indicateurs"
			},
			"$key": "1D62AC47861FD30ACF3398A5315767526E7F3B8A"
		},
		"pageLayout.e4cd4586-4ddd-4fb9-8b03-5b5783068390.@5a82b917-9d77-4ab4-961b-85e116aaa7c3": {
			"chp": 10036,
			"id": 135,
			"text": {
				"en-us": "Business Process",
				"fr-fr": "Processus"
			},
			"$key": "0D456FD3DF5760864F1BF1CB34035E986E02A638"
		},
		"pageLayout.e4cd4586-4ddd-4fb9-8b03-5b5783068390.@d1763c33-34ea-4a05-a18d-c96ee84afc30": {
			"chp": 10036,
			"id": 136,
			"text": {
				"en-us": "Key Information",
				"de-de": "Schlüsselinformationen",
				"es-es": "Indicadores",
				"fr-fr": "Indicateurs",
				"it-it": "Informazioni chiave",
				"pt-pt": "Informação chave"
			},
			"$key": "9FD0F74EE8037171EE9E28744A968926917482F8"
		},
		"pageLayout.e4cd4586-4ddd-4fb9-8b03-5b5783068390.@c93d227c-c51d-4b27-8e7d-8afdf5d1fa64": {
			"chp": 10036,
			"id": 137,
			"text": {
				"en-us": "Business process",
				"de-de": "Geschäftsprozess",
				"es-es": "Procesos",
				"fr-fr": "Processus",
				"it-it": "Business process",
				"pt-pt": "Processo de negócio"
			},
			"$key": "697994977AAAB19F58770FDE282EC76AAC3B3246"
		},
		"pageLayout.17c59885-2c1a-4184-a15b-2a2b55925b30.@f71c59a0-84ce-41af-ad6d-1aa8b05ad7a9": {
			"chp": 10036,
			"id": 138,
			"text": {
				"en-us": "Key Information",
				"fr-fr": "Indicateurs"
			},
			"$key": "6A3CDB0E1C2028F5174949D5A713385E963E364F"
		},
		"pageLayout.17c59885-2c1a-4184-a15b-2a2b55925b30.@1736f803-754c-4f85-8685-ac6af7f4671f": {
			"chp": 10036,
			"id": 139,
			"text": {
				"en-us": "Business Process",
				"fr-fr": "Processus"
			},
			"$key": "1AC7EC6CCEF42818708DECCF7D22BB9D5BC0E564"
		},
		"pageLayout.17c59885-2c1a-4184-a15b-2a2b55925b30.@6c81f19b-c34d-4167-b355-4feaa27be744": {
			"chp": 10036,
			"id": 140,
			"text": {
				"en-us": "Key information",
				"de-de": "Schlüsselinformationen",
				"es-es": "Indicadores",
				"fr-fr": "Indicateurs",
				"it-it": "Informazioni chiave",
				"pt-pt": "Informação chave"
			},
			"$key": "B4B67F90D5F83976BBC522D6DDE969370823D8FD"
		},
		"pageLayout.17c59885-2c1a-4184-a15b-2a2b55925b30.@c77edce5-a1ba-4e5c-8e9b-a3f4ae329660": {
			"chp": 10036,
			"id": 141,
			"text": {
				"en-us": "Business process",
				"de-de": "Geschäftsprozess",
				"es-es": "Procesos",
				"fr-fr": "Processus",
				"it-it": "Business process",
				"pt-pt": "Processo de negócio"
			},
			"$key": "D494953019BD769A8F5EA16246990A0F783E40A6"
		},
		"pageLayout.17c59885-2c1a-4184-a15b-2a2b55925b30.@ecb8d9fe-e4a3-48a1-b769-709286f02c87": {
			"chp": 10036,
			"id": 142,
			"text": {
				"en-us": "New Tab 1"
			},
			"$key": "C033A15AB921ECCDAAD16EF6F768E43DD9E6BD3E"
		},
		"pageLayout.ff7f2c8b-dd3a-43b0-a9ec-fef473cb17b1.@2ac34558-2433-40db-b31b-a60aad9801e9": {
			"chp": 10036,
			"id": 143,
			"text": {
				"en-us": "Business Process",
				"de-de": "Geschäftsprozess",
				"es-es": "Procesos",
				"fr-fr": "Processus",
				"it-it": "Business process",
				"pt-pt": "Processo de negócio"
			},
			"$key": "A185497DD431F0CA9B43CDDBC252497A8C373613"
		},
		"pageLayout.ff7f2c8b-dd3a-43b0-a9ec-fef473cb17b1.@ddf9812a-9414-44a2-8ce7-fdc2e51f9fd2": {
			"chp": 10036,
			"id": 144,
			"text": {
				"en-us": "Key Information",
				"de-de": "Schlüsselinformationen",
				"es-es": "Indicadores",
				"fr-fr": "Indicateurs",
				"it-it": "Informazioni chiave",
				"pt-pt": "Informação chave"
			},
			"$key": "2F12726981D4F15ED463B609BA154DEBD55746FD"
		},
		"pageLayout.db0a9dc6-b5d5-4278-8f51-ee99043df2b0.@d691a6af-ed22-4b84-99a2-c0f94d45c53f": {
			"chp": 10036,
			"id": 145,
			"text": {
				"de-de": "New Tab 1"
			},
			"$key": "EC6E2EF53F128DE1C24B780E9D4C0F247CB3CD35"
		},
		"pageLayout.db0a9dc6-b5d5-4278-8f51-ee99043df2b0.@48736c07-f3da-48ea-b54c-6735400f8643": {
			"chp": 10036,
			"id": 146,
			"text": {
				"de-de": "New Tab 2"
			},
			"$key": "1DDFA58DE79D4EC21E46E24397EEA8CC799157A0"
		},
		"pageLayout.db0a9dc6-b5d5-4278-8f51-ee99043df2b0.@21ec8c71-9746-4ece-9b5a-166fe15f658f": {
			"chp": 10036,
			"id": 147,
			"text": {
				"de-de": "New Tab 3"
			},
			"$key": "9BEE44F99FF564B2B8A192C55942C1C298481447"
		},
		"pageLayout.9906abe4-1449-4b6b-9d6c-78caf30b6171.@70a0261a-c541-40bc-bf04-88a82e82dbab": {
			"chp": 10036,
			"id": 148,
			"text": {
				"de-de": "New Tab 1"
			},
			"$key": "AEC699BD0DA1DED9F88722CFC41EC17403333B3E"
		},
		"pageLayout.fd67a248-fcd0-40e0-a094-0f453bd036de.@5472c870-19fb-4e6b-bc23-a8385c46bf04": {
			"chp": 10036,
			"id": 149,
			"text": {
				"fr-fr": "New Tab 1"
			},
			"$key": "2CEB1654162637EC66741B22464B854D297E500D"
		}
	}
}